pywig/__init__.py
pywig/templates.py
pywig/webpage.py
pywig-0.1.0.dist-info/LICENSE.txt
pywig-0.1.0.dist-info/METADATA
pywig-0.1.0.dist-info/WHEEL
pywig-0.1.0.dist-info/top_level.txt
pywig-0.1.0.dist-info/RECORD
