Metadata-Version: 2.1
Name: pywig
Version: 0.1.0
Summary: A Python package made to create HTML files and web pages seamlessly.
Home-page: https://github.com/BobBrown1/pywig
License: UNKNOWN
Project-URL: Bug Tracker, https://github.com/BobBrown1/pywig/issues
Platform: UNKNOWN
Classifier: Programming Language :: Python :: 3
Classifier: License :: OSI Approved :: MIT License
Classifier: Operating System :: OS Independent
Requires-Python: >=3.6
License-File: LICENSE.txt
Requires-Dist: regex
Requires-Dist: selenium
